static_data/DataStore.py
static_data/__init__.py
static_data/ddragon.py
static_data/patch.py
static_data-0.10.0.dist-info/LICENSE
static_data-0.10.0.dist-info/METADATA
static_data-0.10.0.dist-info/WHEEL
static_data-0.10.0.dist-info/top_level.txt
static_data-0.10.0.dist-info/RECORD
