Metadata-Version: 2.1
Name: static-data
Version: 0.10.0
Summary: Library to easily handles ddragon ressources files for League of Legends
Home-page: https://github.com/Canisback/static-data
Author: Canisback
Author-email: canisback@gmail.com
License: UNKNOWN
Keywords: Riot API,python,static-data
Platform: UNKNOWN
Requires-Dist: requests
Requires-Dist: asyncio
Requires-Dist: aiohttp
